djproxy/__init__.py
djproxy/headers.py
djproxy/models.py
djproxy/proxy_middleware.py
djproxy/request.py
djproxy/urls.py
djproxy/util.py
djproxy/views.py
djproxy-2.3.6.dist-info/LICENSE
djproxy-2.3.6.dist-info/METADATA
djproxy-2.3.6.dist-info/WHEEL
djproxy-2.3.6.dist-info/top_level.txt
djproxy-2.3.6.dist-info/RECORD
