Metadata-Version: 2.1
Name: djproxy
Version: 2.3.6
Summary: djproxy is a simple reverse proxy class-based generic view for Django apps.
Home-page: https://github.com/thomasw/djproxy
Author: Thomas Welfley
Author-email: thomas.welfley+djproxy@gmail.com
License: MIT
Platform: UNKNOWN
Classifier: Development Status :: 5 - Production/Stable
Classifier: Intended Audience :: Developers
Classifier: License :: OSI Approved :: MIT License
Classifier: Topic :: Software Development :: Libraries
Classifier: Framework :: Django :: 1.11
Classifier: Framework :: Django :: 2.1
Classifier: Framework :: Django :: 2.2
Classifier: Framework :: Django :: 3.0
Classifier: Framework :: Django :: 3.1
Classifier: Programming Language :: Python
Classifier: Programming Language :: Python :: 2.7
Classifier: Programming Language :: Python :: 3.5
Classifier: Programming Language :: Python :: 3.6
Classifier: Programming Language :: Python :: 3.7
Classifier: Programming Language :: Python :: 3.8
Classifier: Programming Language :: Python :: Implementation :: PyPy
Requires-Dist: requests (>=1.0.0)
Requires-Dist: django (>=1.11)
Requires-Dist: six (>=1.9.0)
